Metadata-Version: 2.1
Name: ak_ifa
Version: 0.1.1
Summary: Incremental Feature Analysis Tool
Home-page: https://github.com/AviadKlein/ifa
Author: Aviad Klein
Author-email: Aviad Klein <aviad.klein@gmail.com>
Project-URL: Homepage, https://github.com/AviadKlein/ifa
Classifier: Programming Language :: Python :: 3
Classifier: License :: OSI Approved :: MIT License
Classifier: Operating System :: OS Independent
Requires-Python: >=3.11
License-File: LICENSE
